factom_sdk/__init__.py
factom_sdk/client/__init__.py
factom_sdk/client/anchors_client.py
factom_sdk/client/api_info_client.py
factom_sdk/client/chains_client.py
factom_sdk/client/entries_client.py
factom_sdk/client/factom_client.py
factom_sdk/client/identities_client.py
factom_sdk/client/receipts_client.py
factom_sdk/request_handler/__init__.py
factom_sdk/request_handler/request_handler.py
factom_sdk/utils/__init__.py
factom_sdk/utils/common_util.py
factom_sdk/utils/consts.py
factom_sdk/utils/key_common.py
factom_sdk/utils/utils.py
factom_sdk/utils/validate_signature_util.py
factom_sdk/utils/identities/__init__.py
factom_sdk/utils/identities/identities_key_util.py
factom_harmony_connect-1.2.0.dist-info/LICENSE
factom_harmony_connect-1.2.0.dist-info/METADATA
factom_harmony_connect-1.2.0.dist-info/WHEEL
factom_harmony_connect-1.2.0.dist-info/top_level.txt
factom_harmony_connect-1.2.0.dist-info/RECORD
