Metadata-Version: 2.1
Name: factom-harmony-connect
Version: 1.2.0
Summary: Factom Harmony Connect SDK
Home-page: https://github.com/FactomProject/factom-harmony-connect-python-sdk
Author: Factom, Inc.
Author-email: harmony-support@factom.com
License: UNKNOWN
Keywords: factom,factom-blockchain,blockchain,blockchain-as-a-service,SDK,Harmony Connect
Platform: UNKNOWN
Classifier: Programming Language :: Python :: 3
Classifier: Programming Language :: Python :: 3.4
Classifier: Programming Language :: Python :: 3.5
Classifier: Programming Language :: Python :: 3.6
Classifier: License :: OSI Approved :: MIT License
Classifier: Operating System :: OS Independent
Requires-Dist: base58 (>=1.0.3)
Requires-Dist: ed25519 (>=1.4)
Requires-Dist: validators (>=0.12)
Requires-Dist: requests (>=2.21)
